cedar_mcp/__init__.py
cedar_mcp/__main__.py
cedar_mcp/external_api.py
cedar_mcp/model.py
cedar_mcp/processing.py
cedar_mcp/server.py
bach_cedar_mcp-1.0.1.dist-info/METADATA
bach_cedar_mcp-1.0.1.dist-info/WHEEL
bach_cedar_mcp-1.0.1.dist-info/entry_points.txt
bach_cedar_mcp-1.0.1.dist-info/licenses/LICENSE
bach_cedar_mcp-1.0.1.dist-info/RECORD
