Metadata-Version: 2.4
Name: bach-cedar-mcp
Version: 1.0.1
Summary: A Model Context Protocol server for interacting with CEDAR metadata repository
Project-URL: Homepage, https://github.com/BACH-AI-Tools/cedar-mcp
Project-URL: Documentation, https://github.com/BACH-AI-Tools/cedar-mcp#readme
Project-URL: Repository, https://github.com/BACH-AI-Tools/cedar-mcp
Project-URL: Issues, https://github.com/BACH-AI-Tools/cedar-mcp/issues
Author-email: Feng Rongquan <kirifeng@example.com>
License: MIT
License-File: LICENSE
Classifier: Development Status :: 4 - Beta
Classifier: Intended Audience :: Developers
Classifier: License :: OSI Approved :: MIT License
Classifier: Programming Language :: Python :: 3
Classifier: Programming Language :: Python :: 3.10
Classifier: Programming Language :: Python :: 3.11
Classifier: Programming Language :: Python :: 3.12
Requires-Python: >=3.10
Requires-Dist: fastmcp
Requires-Dist: pydantic>=2.0.0
Requires-Dist: python-dotenv
Requires-Dist: pyyaml>=6.0.0
Requires-Dist: requests
